anaparser/__init__.py
anaparser/anaplan_parser.py
anaparser/module_test.py
anaparser/М60.01_CONS.csv
anaparser-1.9.dist-info/METADATA
anaparser-1.9.dist-info/WHEEL
anaparser-1.9.dist-info/top_level.txt
anaparser-1.9.dist-info/RECORD
